README.md
setup.py
topfile_util.py
topfile_util.egg-info/PKG-INFO
topfile_util.egg-info/SOURCES.txt
topfile_util.egg-info/dependency_links.txt
topfile_util.egg-info/entry_points.txt
topfile_util.egg-info/requires.txt
topfile_util.egg-info/top_level.txt