Metadata-Version: 1.0
Name: topfile-util
Version: 0.1
Summary: SaltStack Topfile Utilities
Home-page: UNKNOWN
Author: Austin Godber
Author-email: godber@uberhip.com
License: UNKNOWN
Keywords: saltstack salt topfile utility test check verify
Platform: UNKNOWN
